sqlalchemy_api_handler/__init__.py
sqlalchemy_api_handler/api_errors.py
sqlalchemy_api_handler/api_handler.py
sqlalchemy_api_handler/bases/__init__.py
sqlalchemy_api_handler/bases/accessor.py
sqlalchemy_api_handler/bases/activate.py
sqlalchemy_api_handler/bases/add.py
sqlalchemy_api_handler/bases/delete.py
sqlalchemy_api_handler/bases/errors.py
sqlalchemy_api_handler/bases/modify.py
sqlalchemy_api_handler/bases/save.py
sqlalchemy_api_handler/bases/soft_delete.py
sqlalchemy_api_handler/bases/tasker.py
sqlalchemy_api_handler/mixins/__init__.py
sqlalchemy_api_handler/mixins/activity_mixin.py
sqlalchemy_api_handler/mixins/has_activities_mixin.py
sqlalchemy_api_handler/mixins/needs_validation_mixin.py
sqlalchemy_api_handler/mixins/soft_deletable_mixin.py
sqlalchemy_api_handler/mixins/task_mixin.py
sqlalchemy_api_handler/serialization/__init__.py
sqlalchemy_api_handler/serialization/as_dict.py
sqlalchemy_api_handler/serialization/get_result.py
sqlalchemy_api_handler/serialization/serialize.py
sqlalchemy_api_handler/utils/__init__.py
sqlalchemy_api_handler/utils/asynchronous.py
sqlalchemy_api_handler/utils/attr_dict.py
sqlalchemy_api_handler/utils/date.py
sqlalchemy_api_handler/utils/datum.py
sqlalchemy_api_handler/utils/dehumanize.py
sqlalchemy_api_handler/utils/humanize.py
sqlalchemy_api_handler/utils/is_id_column.py
sqlalchemy_api_handler/utils/keywords.py
sqlalchemy_api_handler/utils/load_or_404.py
sqlalchemy_api_handler/utils/logger.py
SQLAlchemy_Api_Handler-0.17.6.dist-info/LICENSE
SQLAlchemy_Api_Handler-0.17.6.dist-info/METADATA
SQLAlchemy_Api_Handler-0.17.6.dist-info/WHEEL
SQLAlchemy_Api_Handler-0.17.6.dist-info/top_level.txt
SQLAlchemy_Api_Handler-0.17.6.dist-info/RECORD
