Metadata-Version: 2.1
Name: SQLAlchemy-Api-Handler
Version: 0.17.6
Summary: Adds SQLAlchemy support to your Flask application for handle apis.
Home-page: https://github.com/betagouv/sqlalchemy-api-handler
Author: Erwan Ledoux
Author-email: lawanledoux@gmail.com
Maintainer: Ledoux
Maintainer-email: lawanledoux@gmail.com
License: MPL-2.0
Project-URL: Code, https://github.com/betagouv/sqlalchemy-api-handler
Project-URL: Issue tracker, https://github.com/betagouv/sqlalchemy-api-handler/issues
Platform: UNKNOWN
Classifier: Development Status :: 5 - Production/Stable
Classifier: Environment :: Web Environment
Classifier: Intended Audience :: Developers
Classifier: License :: OSI Approved :: Mozilla Public License 2.0 (MPL 2.0)
Classifier: Operating System :: OS Independent
Classifier: Programming Language :: Python
Classifier: Programming Language :: Python :: 2
Classifier: Programming Language :: Python :: 2.7
Classifier: Programming Language :: Python :: 3
Classifier: Programming Language :: Python :: 3.4
Classifier: Programming Language :: Python :: 3.5
Classifier: Programming Language :: Python :: 3.6
Classifier: Programming Language :: Python :: 3.7
Classifier: Programming Language :: Python :: Implementation :: CPython
Classifier: Programming Language :: Python :: Implementation :: PyPy
Classifier: Topic :: Internet :: WWW/HTTP :: Dynamic Content
Classifier: Topic :: Software Development :: Libraries :: Python Modules
Requires-Python: >= 2.7, != 3.0.*, != 3.1.*, != 3.2.*, != 3.3.*
Requires-Dist: inflect (==2.1.0)
Requires-Dist: psycopg2-binary (==2.8.4)
Requires-Dist: sqlalchemy (==1.3.13)
Requires-Dist: SQLAlchemy (==1.3.13)
